{"status":"done","publicPath":"http://0.0.0.0:8080/","chunks":{"app":[{"name":"css/app.470440c0.css","publicPath":"http://0.0.0.0:8080/css/app.470440c0.css","path":"C:\\Users\\er_as\\django-project\\gamedatabase\\frontend\\dist\\css\\app.470440c0.css"},{"name":"js/app.0b9b1142.js","publicPath":"http://0.0.0.0:8080/js/app.0b9b1142.js","path":"C:\\Users\\er_as\\django-project\\gamedatabase\\frontend\\dist\\js\\app.0b9b1142.js"},{"name":"css/app.470440c0.css.map","publicPath":"http://0.0.0.0:8080/css/app.470440c0.css.map","path":"C:\\Users\\er_as\\django-project\\gamedatabase\\frontend\\dist\\css\\app.470440c0.css.map"},{"name":"js/app.0b9b1142.js.map","publicPath":"http://0.0.0.0:8080/js/app.0b9b1142.js.map","path":"C:\\Users\\er_as\\django-project\\gamedatabase\\frontend\\dist\\js\\app.0b9b1142.js.map"}]}}